gracefully_kill/README.MD
gracefully_kill/__init__.py
gracefully_kill/requirements.txt
gracefully_kill/thirdparty.json
gracefully_kill-0.10.dist-info/LICENSE.rst
gracefully_kill-0.10.dist-info/METADATA
gracefully_kill-0.10.dist-info/WHEEL
gracefully_kill-0.10.dist-info/top_level.txt
gracefully_kill-0.10.dist-info/RECORD
