Metadata-Version: 2.1
Name: gracefully-kill
Version: 0.10
Summary: Terminates a subprocess gracefully, if it doesn't work, it will be killed (Windows only)
Home-page: https://github.com/hansalemaos/gracefully_kill
Author: Johannes Fischer
Author-email: aulasparticularesdealemaosp@gmail.com
License: MIT
Keywords: subprocess,kill
Classifier: Development Status :: 4 - Beta
Classifier: Programming Language :: Python :: 3 :: Only
Classifier: Programming Language :: Python :: 3.10
Classifier: Topic :: Software Development :: Libraries :: Python Modules
Classifier: Topic :: Utilities
License-File: LICENSE.rst
Requires-Dist: isa
Requires-Dist: taskkill
